{
  "checked_at": "2026-07-01T15:15:02.648509+00:00",
  "checked_at_human": "2026-07-01 15:15 UTC",
  "prices": {
    "eth_usd": 1609.87,
    "lyx_usd": 0.270996
  },
  "validators": [
    {
      "chain": "ethereum",
      "label": "eth-1165884",
      "index": 1165884,
      "status": "active_ongoing",
      "balance": 32.000582,
      "balance_unit": "ETH",
      "rewards": 0.000582,
      "value_usd": 51516.78,
      "rewards_usd": 0.94,
      "slashed": false,
      "explorer_url": "https://beaconcha.in/validator/1165884"
    },
    {
      "chain": "ethereum",
      "label": "eth-1998776",
      "index": 1998776,
      "status": "active_ongoing",
      "balance": 32.00951,
      "balance_unit": "ETH",
      "rewards": 0.00951,
      "value_usd": 51531.15,
      "rewards_usd": 15.31,
      "slashed": false,
      "explorer_url": "https://beaconcha.in/validator/1998776"
    },
    {
      "chain": "ethereum",
      "label": "eth-1998777",
      "index": 1998777,
      "status": "active_ongoing",
      "balance": 32.009486,
      "balance_unit": "ETH",
      "rewards": 0.009486,
      "value_usd": 51531.11,
      "rewards_usd": 15.27,
      "slashed": false,
      "explorer_url": "https://beaconcha.in/validator/1998777"
    },
    {
      "chain": "ethereum",
      "label": "eth-1998923",
      "index": 1998923,
      "status": "active_ongoing",
      "balance": 32.009455,
      "balance_unit": "ETH",
      "rewards": 0.009455,
      "value_usd": 51531.06,
      "rewards_usd": 15.22,
      "slashed": false,
      "explorer_url": "https://beaconcha.in/validator/1998923"
    },
    {
      "chain": "lukso",
      "label": "humbly-flying-dove",
      "pubkey": "0xa2e5a4723655a8baf3411300d3ff3622903b6a7f79f85fc41193bd83f51afa284a2c8d055e2b0c54c7b46871a8f905cf",
      "status": "active_ongoing",
      "balance": 31.995308,
      "balance_unit": "LYX",
      "rewards": -0.004692,
      "value_usd": 8.67,
      "rewards_usd": -0.0,
      "slashed": false,
      "explorer_url": "https://explorer.consensus.mainnet.lukso.network/validator/0xa2e5a4723655a8baf3411300d3ff3622903b6a7f79f85fc41193bd83f51afa284a2c8d055e2b0c54c7b46871a8f905cf"
    }
  ],
  "issues": [],
  "totals": {
    "validators": 5,
    "eth_count": 4,
    "lukso_count": 1,
    "eth_balance": 128.029,
    "lyx_balance": 31.9953,
    "eth_rewards": 0.029,
    "lyx_rewards": -0.0047,
    "value_usd": 206118.77,
    "rewards_usd": 46.74
  },
  "status": "ok"
}